{
    "B00004": {
        "image": "https://i.imgur.com/54Pgmsp.jpg",
        "weight": "20g",
        "style": "Bar",
        "date_poured": "2019-05-04T00:00:00-0500"
    },
    "B00005": {
        "image": "https://i.imgur.com/0EnPaBU.jpg",
        "weight": "20g",
        "style": "Bar",
        "date_poured": "2019-05-04T00:00:00-0500"
    },
    "B00006": {
        "image": "https://i.imgur.com/KogO88P.jpg",
        "weight": "20g",
        "style": "",
        "date_poured": "2019-05-04T00:00:00-0500"
    },
    "B00007": {
        "image": "https://i.imgur.com/3dmTt4A.jpg",
        "weight": "12g",
        "style": "Bar-Skinny",
        "date_poured": "2019-05-04T00:00:00-0500"
    },
    "B00008": {
        "image": "https://i.imgur.com/UDtu7kn.jpg",
        "weight": "13g",
        "style": "bar-Skiny",
        "date_poured": "2019-05-04T00:00:00-0500"
    },
    "B00009": {
        "image": "https://i.imgur.com/GFonEpf.jpg",
        "weight": "15g",
        "style": "Bar-Rounded",
        "date_poured": "2019-05-04T00:00:00-0500"
    },
    "B00010": {
        "image": "https://i.imgur.com/6w8F9Rt.jpg",
        "weight": "19g",
        "style": "Bar",
        "date_poured": "2019-05-04T00:00:00-0500"
    },
    "B00011": {
        "image": "https://i.imgur.com/6w8F9Rt.jpg",
        "weight": "19g",
        "style": "Bar",
        "date_poured": "2019-05-04T00:00:00-0500"
    },
    "B00012": {
        "image": "https://i.imgur.com/rjxHbiR.jpg",
        "weight": "79g",
        "style": "Bar",
        "date_poured": "2019-05-11T00:00:00-0500"
    },
    "B00013": {
        "image": "https://i.imgur.com/Q1wCFT4.jpg",
        "weight": "58g",
        "style": "Bar",
        "date_poured": "2019-05-17T00:00:00-0500"
    },
    "CB00001": {
        "image": "https://i.imgur.com/QspWgUR.jpg",
        "weight": "31g",
        "style": "Bar",
        "date_poured": "2019-05-14T00:00:00-0500"
    },
    "CB00002": {
        "image": "https://i.imgur.com/FtDRFHf.jpg",
        "weight": "28g",
        "style": "Bar",
        "date_poured": "2019-05-17T00:00:00-0500"
    },
    "CB00003": {
        "image": "https://i.imgur.com/THj3sDq.jpg",
        "weight": "33g",
        "style": "Bar",
        "date_poured": "2019-05-17T00:00:00-0500"
    },
    "P00001": {
        "image": "https://i.imgur.com/foPWTyP.jpg",
        "weight": "8g",
        "style": "Penis",
        "date_poured": "2019-05-01T00:00:00-0500"
    },
    "P00002": {
        "image": "https://i.imgur.com/53GqlV2.jpg",
        "weight": "7g",
        "style": "Penis",
        "date_poured": "2019-04-04T00:00:00-0500"
    },
    "P00003": {
        "image": "https://i.imgur.com/Y7HDGbw.jpg",
        "weight": "33g",
        "style": "Penis",
        "date_poured": "2019-05-04T00:00:00-0500"
    },
    "P00004": {
        "image": "https://i.imgur.com/9NmUm41.jpg",
        "weight": "18g",
        "style": "Penis",
        "date_poured": "2019-05-04T00:00:00-0500"
    },
    "P00005": {
        "image": "https://i.imgur.com/VuRIVpe.jpg",
        "weight": "34g",
        "style": "Penis",
        "date_poured": "2019-05-09T00:00:00-0500"
    },
    "R00003": {
        "image": "https://i.imgur.com/GLRmSB2.jpg",
        "weight": "9g",
        "style": "Round",
        "date_poured": "2019-05-11T00:00:00-0500"
    },
    "R00004": {
        "image": "https://i.imgur.com/vewwoA5.jpg",
        "weight": "10g",
        "style": "Round",
        "date_poured": "2019-05-11T00:00:00-0500"
    },
    "R00005": {
        "image": "https://i.imgur.com/JUAK95D.jpg",
        "weight": "5g",
        "style": "Round",
        "date_poured": "2019-05-11T00:00:00-0500"
    },
    "R00006": {
        "image": "https://i.imgur.com/fXsMMG0.jpg",
        "weight": "25g",
        "style": "Round",
        "date_poured": "2019-05-11T00:00:00-0500"
    },
    "R00007": {
        "image": "https://i.imgur.com/asaw2dQ.jpg",
        "weight": "29g",
        "style": "Round",
        "date_poured": "2019-05-11T00:00:00-0500"
    },
    "R00008": {
        "image": "https://i.imgur.com/QI89iT1.jpg",
        "weight": "21g",
        "style": "Round",
        "date_poured": "2019-05-11T00:00:00-0500"
    },
    "R00009": {
        "image": "https://i.imgur.com/6LclCud.jpg",
        "weight": "20g",
        "style": "Round",
        "date_poured": "2019-05-11T00:00:00-0500"
    },
    "R00010": {
        "image": "https://i.imgur.com/XkheCcK.jpg",
        "weight": "24g",
        "style": "Round",
        "date_poured": "2019-05-11T00:00:00-0500"
    },
    "R00011": {
        "image": "https://i.imgur.com/CuFPVH7.jpg",
        "weight": "4g",
        "style": "Round",
        "date_poured": "2019-05-11T00:00:00-0500"
    },
    "R00012": {
        "image": "https://i.imgur.com/MaMKwOu.jpg",
        "weight": "30g",
        "style": "Round",
        "date_poured": "2019-05-14T00:00:00-0500"
    },
    "R00013": {
        "image": "https://i.imgur.com/IGhQBIa.jpg",
        "weight": "30g",
        "style": "Round",
        "date_poured": "2019-05-14T00:00:00-0500"
    },
    "R00014": {
        "image": "https://i.imgur.com/akZJTdM.jpg?1",
        "weight": "35g",
        "style": "Round",
        "date_poured": "2019-05-14T00:00:00-0500"
    },
    "R00015": {
        "image": "https://i.imgur.com/FEh0HuB.jpg?1",
        "weight": "34g",
        "style": "Round",
        "date_poured": "2019-05-14T00:00:00-0500"
    },
    "R00016": {
        "image": "https://i.imgur.com/Vqy6OST.jpg",
        "weight": "22g",
        "style": "Round",
        "date_poured": "2019-05-17T00:00:00-0500"
    },
    "S0001": {
        "image": "https://i.imgur.com/1AOBuqR.jpg",
        "weight": "19g",
        "style": "Square",
        "date_poured": "2019-05-17T00:00:00-0500"
    },
    "S0002": {
        "image": "https://i.imgur.com/q5e6bEY.jpg",
        "weight": "24g",
        "style": "Square",
        "date_poured": "2019-05-17T00:00:00-0500"
    },
    "SF0001": {
        "image": "https://i.imgur.com/NGJyBMb.jpg",
        "weight": "50g",
        "style": "Stick Figure",
        "date_poured": "2019-05-15T00:00:00-0500"
    },
    "SF0002": {
        "image": "https://i.imgur.com/mgHzdcr.jpg",
        "weight": "44g",
        "style": "Stick Figure",
        "date_poured": "2019-05-15T00:00:00-0500"
    }
}